goat_plugins/jsonrpc/__init__.py
goat_plugins/jsonrpc/parameters.py
goat_plugins/jsonrpc/service.py
goat_sdk_plugin_jsonrpc-0.1.2.dist-info/METADATA
goat_sdk_plugin_jsonrpc-0.1.2.dist-info/WHEEL
goat_sdk_plugin_jsonrpc-0.1.2.dist-info/RECORD
